MANIFEST.in
README.rst
setup.py
farm_news.egg-info/PKG-INFO
farm_news.egg-info/SOURCES.txt
farm_news.egg-info/dependency_links.txt
farm_news.egg-info/not-zip-safe
farm_news.egg-info/requires.txt
farm_news.egg-info/top_level.txt
news/__init__.py
news/admin.py
news/cms_app.py
news/context_processors.py
news/forms.py
news/models.py
news/urls.py
news/views.py
news/migrations/0001_initial.py
news/migrations/__init__.py
news/templates/news/article_detail.html
news/templates/news/article_list.html
news/templates/news/latest_articles.html